buildcompiler/__init__.py
buildcompiler/abstract_translator.py
buildcompiler/buildcompiler.py
buildcompiler/constants.py
buildcompiler/robotutils.py
buildcompiler/sbol2build.py
synbio_buildcompiler-0.0b1.dist-info/licenses/LICENSE
synbio_buildcompiler-0.0b1.dist-info/METADATA
synbio_buildcompiler-0.0b1.dist-info/WHEEL
synbio_buildcompiler-0.0b1.dist-info/top_level.txt
synbio_buildcompiler-0.0b1.dist-info/RECORD
