Metadata-Version: 2.4
Name: synbio_buildcompiler
Version: 0.0b1
Summary: BuildCompiler is a package to decouple the design and build stages
Author-email: Gonzalo Vidal <gonzalo.vidalpena@colorado.edu>, Ryan Greer <ryan.greer@colorado.edu>
Maintainer-email: Ryan Greer <ryan.greer@colorado.edu>
Project-URL: Homepage, https://github.com/MyersResearchGroup/BuildCompiler
Project-URL: Bug Tracker, https://github.com/MyersResearchGroup/BuildCompiler/issues
Keywords: SBOL,genetic,automation,build,synthetic biology
Classifier: Programming Language :: Python :: 3
Classifier: License :: OSI Approved :: MIT License
Classifier: Operating System :: OS Independent
Requires-Python: >=3.10
License-File: LICENSE
Requires-Dist: sbol2
Requires-Dist: biopython
Requires-Dist: pydna
Provides-Extra: test
Requires-Dist: pytest<5.0.0; extra == "test"
Requires-Dist: pytest-cov[all]; extra == "test"
Dynamic: license-file
